Topsis_Hemang_101916107/Topsis.py
Topsis_Hemang_101916107/__init__.py
Hemang_17-0.0.1.dist-info/METADATA
Hemang_17-0.0.1.dist-info/WHEEL
Hemang_17-0.0.1.dist-info/top_level.txt
Hemang_17-0.0.1.dist-info/RECORD
