Metadata-Version: 2.1
Name: Hemang-17
Version: 0.0.1
Summary: Topsis implementation
Home-page: UNKNOWN
Author: Hemang
Author-email: <hemang.popli7@gmail.com>
License: UNKNOWN
Keywords: python,topsis,impacts,video,stream,video stream,camera stream,sockets
Platform: UNKNOWN
Classifier: Development Status :: 1 - Planning
Classifier: Intended Audience :: Developers
Classifier: Programming Language :: Python :: 3
Classifier: Operating System :: Unix
Classifier: Operating System :: MacOS :: MacOS X
Classifier: Operating System :: Microsoft :: Windows
Requires-Dist: topsispy
Requires-Dist: numpy
Requires-Dist: pandas
